linemark/__init__.py
linemark/__main__.py
linemark/_version.py
linemark/py.typed
linemark/adapters/__init__.py
linemark/adapters/filesystem.py
linemark/adapters/read_type_adapter.py
linemark/adapters/search_adapter.py
linemark/adapters/slugifier.py
linemark/adapters/sqid_generator.py
linemark/adapters/write_type_adapter.py
linemark/cli/__init__.py
linemark/cli/formatters.py
linemark/cli/main.py
linemark/domain/__init__.py
linemark/domain/entities.py
linemark/domain/exceptions.py
linemark/domain/search.py
linemark/ports/__init__.py
linemark/ports/filesystem.py
linemark/ports/read_type.py
linemark/ports/search.py
linemark/ports/slugifier.py
linemark/ports/sqid_generator.py
linemark/ports/write_type.py
linemark/use_cases/__init__.py
linemark/use_cases/add_node.py
linemark/use_cases/compact_outline.py
linemark/use_cases/compile_doctype.py
linemark/use_cases/delete_node.py
linemark/use_cases/list_outline.py
linemark/use_cases/manage_types.py
linemark/use_cases/move_node.py
linemark/use_cases/read_type.py
linemark/use_cases/rename_node.py
linemark/use_cases/search.py
linemark/use_cases/validate_outline.py
linemark/use_cases/write_type.py
linemark-0.2.2.dist-info/METADATA
linemark-0.2.2.dist-info/WHEEL
linemark-0.2.2.dist-info/entry_points.txt
linemark-0.2.2.dist-info/licenses/LICENSE.md
linemark-0.2.2.dist-info/RECORD
